matrixcalc/Errors.py
matrixcalc/Matrix.py
matrixcalc/Row.py
matrixcalc/__init__.py
matrixcalc/app.py
matrixcalc/command_line.py
matrixcalc/hooks.py
matrixcalc/main.py
MatrixCalcs-1.0.1.dist-info/LICENSE.txt
MatrixCalcs-1.0.1.dist-info/METADATA
MatrixCalcs-1.0.1.dist-info/WHEEL
MatrixCalcs-1.0.1.dist-info/entry_points.txt
MatrixCalcs-1.0.1.dist-info/top_level.txt
MatrixCalcs-1.0.1.dist-info/RECORD
