Metadata-Version: 2.1
Name: MatrixCalcs
Version: 1.0.1
Summary: A matrix calculator in your command line.
Home-page: https://github.com/matjohn10/MatrixCalculator
Author: Mathieu Johnson
Author-email: mathieujohnson10@gmail.com
License: MIT
Platform: UNKNOWN
Classifier: License :: OSI Approved :: MIT License
Classifier: Programming Language :: Python :: 3.10
Requires-Python: >=3.10
License-File: LICENSE.txt
Requires-Dist: numpy (>=1.26.2)
Provides-Extra: dev
Requires-Dist: pytest (>=7.4) ; extra == 'dev'
Requires-Dist: twine (>=4.0.2) ; extra == 'dev'
